jinja2_library/__init__.py
jinja2_library/template_lib.py
jinja2_library-0.5.1.dist-info/licenses/LICENSE
jinja2_library-0.5.1.dist-info/METADATA
jinja2_library-0.5.1.dist-info/WHEEL
jinja2_library-0.5.1.dist-info/top_level.txt
jinja2_library-0.5.1.dist-info/zip-safe
jinja2_library-0.5.1.dist-info/RECORD
